napalm_aruba/__init__.py
napalm_aruba/device.py
napalm_aruba/dialer.py
napalm_aruba/driver.py
napalm_aruba/records.py
napalm_aruba/templates/__init__.py
napalm_aruba/templates/reader.py
napalm_aruba/templates/assets/__init__.py
napalm_aruba/templates/assets/display-device-manuinfo
napalm_aruba/templates/assets/display-device-manuinfo_example
napalm_aruba/templates/assets/interfaces-brief
napalm_aruba/templates/assets/interfaces-brief_example
napalm_aruba/templates/assets/lldp-info-local-device
napalm_aruba/templates/assets/lldp-info-local-device_example
napalm_aruba/templates/assets/lldp-info-remote-device
napalm_aruba/templates/assets/lldp-info-remote-device_example
napalm_aruba/templates/assets/system-information
napalm_digineo_procurve/__init__.py
napalm_digineo_procurve/device.py
napalm_digineo_procurve/dialer.py
napalm_digineo_procurve/driver.py
napalm_digineo_procurve/queries/__init__.py
napalm_digineo_procurve/queries/device_info.py
napalm_digineo_procurve/queries/interfaces.py
napalm_digineo_procurve/queries/lldp_neighbors.py
napalm_digineo_procurve/queries/mib.py
napalm_digineo_procurve/queries/system_info.py
napalm_digineo_procurve/queries/uptime.py
napalm_digineo_procurve/templates/__init__.py
napalm_digineo_procurve/templates/parser.py
napalm_digineo_procurve/templates/reader.py
napalm_digineo_procurve/templates/assets/__init__.py
napalm_digineo_procurve/templates/assets/display-device-manuinfo
napalm_digineo_procurve/templates/assets/interfaces-brief
napalm_digineo_procurve/templates/assets/lldp-info-remote-device
napalm_digineo_procurve/templates/assets/system-information
napalm_digineo_procurve-0.2.0.dist-info/LICENSE.md
napalm_digineo_procurve-0.2.0.dist-info/METADATA
napalm_digineo_procurve-0.2.0.dist-info/WHEEL
napalm_digineo_procurve-0.2.0.dist-info/top_level.txt
napalm_digineo_procurve-0.2.0.dist-info/zip-safe
napalm_digineo_procurve-0.2.0.dist-info/RECORD
