Metadata-Version: 2.1
Name: napalm-digineo-procurve
Version: 0.2.0
Summary: napalm driver for aruba procurve switches
Home-page: https://github.com/digineo/napalm-digineo-procurve
Maintainer: Arthur Skowronek
Maintainer-email: ags@digineo.de
License: Apache Software License 2.0
Project-URL: Bug Tracker, https://github.com/digineo/napalm-digineo-procurve/issues
Project-URL: Source Code, https://github.com/digineo/napalm-digineo-procurve/
Platform: UNKNOWN
Classifier: Development Status :: 5 - Production/Stable
Classifier: Intended Audience :: System Administrators
Classifier: License :: OSI Approved
Classifier: License :: OSI Approved :: Apache Software License
Classifier: Programming Language :: Python
Classifier: Programming Language :: Python :: 3
Classifier: Programming Language :: Python :: 3.5
Classifier: Programming Language :: Python :: 3.6
Classifier: Programming Language :: Python :: 3.7
Classifier: Topic :: System
Classifier: Topic :: System :: Networking
Classifier: Topic :: System :: Networking :: Monitoring
Requires-Dist: attrs (~=19.1.0)
Requires-Dist: importlib-resources (~=1.0.2)
Requires-Dist: napalm (~=2.4.0)
